MANIFEST.in
README.md
setup.py
seislab/LICENSE.txt
seislab/README.md
seislab/__init__.py
seislab.egg-info/PKG-INFO
seislab.egg-info/SOURCES.txt
seislab.egg-info/dependency_links.txt
seislab.egg-info/requires.txt
seislab.egg-info/top_level.txt
seislab/demo/example.py
seislab/demo/seismic.segy
seislab/demo/seismic_reverse.segy
seislab/src/__init__.py
seislab/src/analysis.py
seislab/src/inputoutput.py
seislab/src/__pycache__/__init__.cpython-36.pyc
seislab/src/__pycache__/analysis.cpython-36.pyc
seislab/src/__pycache__/inputoutput.cpython-36.pyc
seislab/src/__pycache__/seispy.cpython-36.pyc
seislab/src/segpy/About segpy.txt
seislab/src/segpy/__init__.py
seislab/src/segpy/binary_reel_header.py
seislab/src/segpy/catalog.py
seislab/src/segpy/datatypes.py
seislab/src/segpy/docstring.py
seislab/src/segpy/encoding.py
seislab/src/segpy/header.py
seislab/src/segpy/ibm_float.py
seislab/src/segpy/packer.py
seislab/src/segpy/reader.py
seislab/src/segpy/revisions.py
seislab/src/segpy/textual_reel_header.py
seislab/src/segpy/toolkit.py
seislab/src/segpy/trace_header.py
seislab/src/segpy/types.py
seislab/src/segpy/util.py
seislab/src/segpy/writer.py
seislab/src/segpy/__pycache__/__init__.cpython-35.pyc
seislab/src/segpy/__pycache__/__init__.cpython-36.pyc
seislab/src/segpy/__pycache__/binary_reel_header.cpython-35.pyc
seislab/src/segpy/__pycache__/binary_reel_header.cpython-36.pyc
seislab/src/segpy/__pycache__/catalog.cpython-35.pyc
seislab/src/segpy/__pycache__/catalog.cpython-36.pyc
seislab/src/segpy/__pycache__/datatypes.cpython-35.pyc
seislab/src/segpy/__pycache__/datatypes.cpython-36.pyc
seislab/src/segpy/__pycache__/docstring.cpython-35.pyc
seislab/src/segpy/__pycache__/docstring.cpython-36.pyc
seislab/src/segpy/__pycache__/encoding.cpython-35.pyc
seislab/src/segpy/__pycache__/encoding.cpython-36.pyc
seislab/src/segpy/__pycache__/header.cpython-35.pyc
seislab/src/segpy/__pycache__/header.cpython-36.pyc
seislab/src/segpy/__pycache__/ibm_float.cpython-35.pyc
seislab/src/segpy/__pycache__/ibm_float.cpython-36.pyc
seislab/src/segpy/__pycache__/packer.cpython-35.pyc
seislab/src/segpy/__pycache__/packer.cpython-36.pyc
