Metadata-Version: 2.1
Name: seislab
Version: 1.0.0
Summary: A python toolbox for seismic data i/o and analysis
Home-page: UNKNOWN
Author: Cognitive Geo
Author-email: cognitivegeo.info@gmail.com
License: UNKNOWN
Keywords: Python,Seismic
Platform: UNKNOWN
Classifier: Development Status :: 3 - Alpha
Classifier: Intended Audience :: Science/Research
Classifier: Topic :: Scientific/Engineering
Classifier: License :: OSI Approved :: GNU Affero General Public License v3 or later (AGPLv3+)
Classifier: Programming Language :: Python :: 3
Classifier: Operating System :: OS Independent
Requires-Python: >=3.5
